idnapi/__init__.py
idnapi/accessprofiles.py
idnapi/accounts.py
idnapi/cc.py
idnapi/entitlements.py
idnapi/idnclient.py
idnapi/oauth.py
idnapi/roles.py
idnapi/search.py
idnapi/workgroups.py
idnapi-0.0.5.dist-info/METADATA
idnapi-0.0.5.dist-info/WHEEL
idnapi-0.0.5.dist-info/top_level.txt
idnapi-0.0.5.dist-info/RECORD
